dyacon/__init__.py
dyacon/read.py
dyacon/loaders/__init__.py
dyacon/loaders/loaders.py
dyacon/loaders/external/__init__.py
dyacon/loaders/external/google.py
dyacon-0.0.10.dist-info/LICENSE
dyacon-0.0.10.dist-info/METADATA
dyacon-0.0.10.dist-info/WHEEL
dyacon-0.0.10.dist-info/top_level.txt
dyacon-0.0.10.dist-info/RECORD
